<config><interface address="10.0.0.0" hosts="hostVIP[0]" names="ppp0" netmask="255.255.255.252" /><interface address="10.0.0.4" hosts="hostVIP[1]" names="ppp0" netmask="255.255.255.252" /><interface address="10.0.0.8" hosts="hostVIP[2]" names="ppp0" netmask="255.255.255.252" /><interface address="10.0.0.12" hosts="hostVIP[3]" names="ppp0" netmask="255.255.255.252" /><interface address="10.0.0.16" hosts="hostVIP[4]" names="ppp0" netmask="255.255.255.252" /><interface address="10.0.0.20" hosts="hostVIP[5]" names="ppp0" netmask="255.255.255.252" /><interface address="10.0.x.x" hosts="router0" netmask="255.255.255.252" towards="hostVIP[*]" /><interface address="10.1.0.0" hosts="hostSSH[0]" names="ppp0" netmask="255.255.255.252" /><interface address="10.1.0.4" hosts="hostSSH[1]" names="ppp0" netmask="255.255.255.252" /><interface address="10.1.0.8" hosts="hostSSH[2]" names="ppp0" netmask="255.255.255.252" /><interface address="10.1.0.12" hosts="hostSSH[3]" names="ppp0" netmask="255.255.255.252" /><interface address="10.1.0.16" hosts="hostSSH[4]" names="ppp0" netmask="255.255.255.252" /><interface address="10.1.0.20" hosts="hostSSH[5]" names="ppp0" netmask="255.255.255.252" /><interface address="10.1.0.24" hosts="hostSSH[6]" names="ppp0" netmask="255.255.255.252" /><interface address="10.1.0.28" hosts="hostSSH[7]" names="ppp0" netmask="255.255.255.252" /><interface address="10.1.0.32" hosts="hostSSH[8]" names="ppp0" netmask="255.255.255.252" /><interface address="10.1.0.36" hosts="hostSSH[9]" names="ppp0" netmask="255.255.255.252" /><interface address="10.1.0.40" hosts="hostSSH[10]" names="ppp0" netmask="255.255.255.252" /><interface address="10.1.0.44" hosts="hostSSH[11]" names="ppp0" netmask="255.255.255.252" /><interface address="10.1.0.48" hosts="hostSSH[12]" names="ppp0" netmask="255.255.255.252" /><interface address="10.1.0.52" hosts="hostSSH[13]" names="ppp0" netmask="255.255.255.252" /><interface address="10.1.0.56" hosts="hostSSH[14]" names="ppp0" netmask="255.255.255.252" /><interface address="10.1.0.60" hosts="hostSSH[15]" names="ppp0" netmask="255.255.255.252" /><interface address="10.1.x.x" hosts="router0" netmask="255.255.255.252" towards="hostSSH[*]" /><interface address="10.2.0.0" hosts="hostVID[0]" names="ppp0" netmask="255.255.255.252" /><interface address="10.2.0.4" hosts="hostVID[1]" names="ppp0" netmask="255.255.255.252" /><interface address="10.2.0.8" hosts="hostVID[2]" names="ppp0" netmask="255.255.255.252" /><interface address="10.2.0.12" hosts="hostVID[3]" names="ppp0" netmask="255.255.255.252" /><interface address="10.2.0.16" hosts="hostVID[4]" names="ppp0" netmask="255.255.255.252" /><interface address="10.2.x.x" hosts="router0" netmask="255.255.255.252" towards="hostVID[*]" /><interface address="10.3.0.0" hosts="hostLVD[0]" names="ppp0" netmask="255.255.255.252" /><interface address="10.3.0.4" hosts="hostLVD[1]" names="ppp0" netmask="255.255.255.252" /><interface address="10.3.0.8" hosts="hostLVD[2]" names="ppp0" netmask="255.255.255.252" /><interface address="10.3.0.12" hosts="hostLVD[3]" names="ppp0" netmask="255.255.255.252" /><interface address="10.3.0.16" hosts="hostLVD[4]" names="ppp0" netmask="255.255.255.252" /><interface address="10.3.x.x" hosts="router0" netmask="255.255.255.252" towards="hostLVD[*]" /><interface address="10.4.0.0" hosts="hostFDO[0]" names="ppp0" netmask="255.255.255.252" /><interface address="10.4.0.4" hosts="hostFDO[1]" names="ppp0" netmask="255.255.255.252" /><interface address="10.4.0.8" hosts="hostFDO[2]" names="ppp0" netmask="255.255.255.252" /><interface address="10.4.0.12" hosts="hostFDO[3]" names="ppp0" netmask="255.255.255.252" /><interface address="10.4.0.16" hosts="hostFDO[4]" names="ppp0" netmask="255.255.255.252" /><interface address="10.4.x.x" hosts="router0" netmask="255.255.255.252" towards="hostFDO[*]" /><interface address="10.10.0.0" hosts="serverVIP" names="ppp0" netmask="255.255.255.252" /><interface address="10.11.0.0" hosts="serverSSH" names="ppp0" netmask="255.255.255.252" /><interface address="10.12.0.0" hosts="serverVID" names="ppp0" netmask="255.255.255.252" /><interface address="10.13.0.0" hosts="serverLVD" names="ppp0" netmask="255.255.255.252" /><interface address="10.14.0.0" hosts="serverFDO" names="ppp0" netmask="255.255.255.252" /><interface address="10.x.x.x" hosts="**" netmask="255.x.x.x" /></config>