<config><class id="root"><parentId>NULL</parentId><rate type="int">20</rate><ceil type="int">20</ceil><burst type="int">1600</burst><cburst type="int">1600</cburst><level type="int">1</level><quantum type="int">1600</quantum><mbuffer type="int">60</mbuffer></class><class id="leafhostVID0"><parentId>innerconnVID</parentId><rate type="int">1000.0</rate><ceil type="int">1250.0</ceil><burst type="int">1600</burst><cburst type="int">1600</cburst><level type="int">0</level><quantum type="int">1600</quantum><mbuffer type="int">60</mbuffer><priority>0</priority><queueNum type="int">0</queueNum></class><class id="leafhostVID1"><parentId>innerconnVID</parentId><rate type="int">1000.0</rate><ceil type="int">1250.0</ceil><burst type="int">1600</burst><cburst type="int">1600</cburst><level type="int">0</level><quantum type="int">1600</quantum><mbuffer type="int">60</mbuffer><priority>0</priority><queueNum type="int">1</queueNum></class><class id="leafhostVID2"><parentId>innerconnVID</parentId><rate type="int">1000.0</rate><ceil type="int">1250.0</ceil><burst type="int">1600</burst><cburst type="int">1600</cburst><level type="int">0</level><quantum type="int">1600</quantum><mbuffer type="int">60</mbuffer><priority>0</priority><queueNum type="int">2</queueNum></class><class id="leafhostVID3"><parentId>innerconnVID</parentId><rate type="int">1000.0</rate><ceil type="int">1250.0</ceil><burst type="int">1600</burst><cburst type="int">1600</cburst><level type="int">0</level><quantum type="int">1600</quantum><mbuffer type="int">60</mbuffer><priority>0</priority><queueNum type="int">3</queueNum></class><class id="leafhostVID4"><parentId>innerconnVID</parentId><rate type="int">1000.0</rate><ceil type="int">1250.0</ceil><burst type="int">1600</burst><cburst type="int">1600</cburst><level type="int">0</level><quantum type="int">1600</quantum><mbuffer type="int">60</mbuffer><priority>0</priority><queueNum type="int">4</queueNum></class><class id="leafhostLVD0"><parentId>innerconnLVD</parentId><rate type="int">2150.0</rate><ceil type="int">2687.5</ceil><burst type="int">1600</burst><cburst type="int">1600</cburst><level type="int">0</level><quantum type="int">1600</quantum><mbuffer type="int">60</mbuffer><priority>0</priority><queueNum type="int">5</queueNum></class><class id="leafhostLVD1"><parentId>innerconnLVD</parentId><rate type="int">2150.0</rate><ceil type="int">2687.5</ceil><burst type="int">1600</burst><cburst type="int">1600</cburst><level type="int">0</level><quantum type="int">1600</quantum><mbuffer type="int">60</mbuffer><priority>0</priority><queueNum type="int">6</queueNum></class><class id="leafhostLVD2"><parentId>innerconnLVD</parentId><rate type="int">2150.0</rate><ceil type="int">2687.5</ceil><burst type="int">1600</burst><cburst type="int">1600</cburst><level type="int">0</level><quantum type="int">1600</quantum><mbuffer type="int">60</mbuffer><priority>0</priority><queueNum type="int">7</queueNum></class><class id="leafhostLVD3"><parentId>innerconnLVD</parentId><rate type="int">2150.0</rate><ceil type="int">2687.5</ceil><burst type="int">1600</burst><cburst type="int">1600</cburst><level type="int">0</level><quantum type="int">1600</quantum><mbuffer type="int">60</mbuffer><priority>0</priority><queueNum type="int">8</queueNum></class><class id="leafhostLVD4"><parentId>innerconnLVD</parentId><rate type="int">2150.0</rate><ceil type="int">2687.5</ceil><burst type="int">1600</burst><cburst type="int">1600</cburst><level type="int">0</level><quantum type="int">1600</quantum><mbuffer type="int">60</mbuffer><priority>0</priority><queueNum type="int">9</queueNum></class><class id="leafhostFDO0"><parentId>innerconnFDO</parentId><rate type="int">800.0</rate><ceil type="int">800.0</ceil><burst type="int">1600</burst><cburst type="int">1600</cburst><level type="int">0</level><quantum type="int">1600</quantum><mbuffer type="int">60</mbuffer><priority>0</priority><queueNum type="int">10</queueNum></class><class id="leafhostFDO1"><parentId>innerconnFDO</parentId><rate type="int">800.0</rate><ceil type="int">800.0</ceil><burst type="int">1600</burst><cburst type="int">1600</cburst><level type="int">0</level><quantum type="int">1600</quantum><mbuffer type="int">60</mbuffer><priority>0</priority><queueNum type="int">11</queueNum></class><class id="leafhostFDO2"><parentId>innerconnFDO</parentId><rate type="int">800.0</rate><ceil type="int">800.0</ceil><burst type="int">1600</burst><cburst type="int">1600</cburst><level type="int">0</level><quantum type="int">1600</quantum><mbuffer type="int">60</mbuffer><priority>0</priority><queueNum type="int">12</queueNum></class><class id="leafhostFDO3"><parentId>innerconnFDO</parentId><rate type="int">800.0</rate><ceil type="int">800.0</ceil><burst type="int">1600</burst><cburst type="int">1600</cburst><level type="int">0</level><quantum type="int">1600</quantum><mbuffer type="int">60</mbuffer><priority>0</priority><queueNum type="int">13</queueNum></class><class id="leafhostFDO4"><parentId>innerconnFDO</parentId><rate type="int">800.0</rate><ceil type="int">800.0</ceil><burst type="int">1600</burst><cburst type="int">1600</cburst><level type="int">0</level><quantum type="int">1600</quantum><mbuffer type="int">60</mbuffer><priority>0</priority><queueNum type="int">14</queueNum></class><class id="leafhostSSH0"><parentId>innerconnSSH</parentId><rate type="int">10.0</rate><ceil type="int">12.5</ceil><burst type="int">1600</burst><cburst type="int">1600</cburst><level type="int">0</level><quantum type="int">1600</quantum><mbuffer type="int">60</mbuffer><priority>0</priority><queueNum type="int">15</queueNum></class><class id="leafhostSSH1"><parentId>innerconnSSH</parentId><rate type="int">10.0</rate><ceil type="int">12.5</ceil><burst type="int">1600</burst><cburst type="int">1600</cburst><level type="int">0</level><quantum type="int">1600</quantum><mbuffer type="int">60</mbuffer><priority>0</priority><queueNum type="int">16</queueNum></class><class id="leafhostSSH2"><parentId>innerconnSSH</parentId><rate type="int">10.0</rate><ceil type="int">12.5</ceil><burst type="int">1600</burst><cburst type="int">1600</cburst><level type="int">0</level><quantum type="int">1600</quantum><mbuffer type="int">60</mbuffer><priority>0</priority><queueNum type="int">17</queueNum></class><class id="leafhostSSH3"><parentId>innerconnSSH</parentId><rate type="int">10.0</rate><ceil type="int">12.5</ceil><burst type="int">1600</burst><cburst type="int">1600</cburst><level type="int">0</level><quantum type="int">1600</quantum><mbuffer type="int">60</mbuffer><priority>0</priority><queueNum type="int">18</queueNum></class><class id="leafhostSSH4"><parentId>innerconnSSH</parentId><rate type="int">10.0</rate><ceil type="int">12.5</ceil><burst type="int">1600</burst><cburst type="int">1600</cburst><level type="int">0</level><quantum type="int">1600</quantum><mbuffer type="int">60</mbuffer><priority>0</priority><queueNum type="int">19</queueNum></class><class id="leafhostSSH5"><parentId>innerconnSSH</parentId><rate type="int">10.0</rate><ceil type="int">12.5</ceil><burst type="int">1600</burst><cburst type="int">1600</cburst><level type="int">0</level><quantum type="int">1600</quantum><mbuffer type="int">60</mbuffer><priority>0</priority><queueNum type="int">20</queueNum></class><class id="leafhostVIP0"><parentId>innerconnVIP</parentId><rate type="int">30.0</rate><ceil type="int">37.5</ceil><burst type="int">1600</burst><cburst type="int">1600</cburst><level type="int">0</level><quantum type="int">1600</quantum><mbuffer type="int">60</mbuffer><priority>0</priority><queueNum type="int">21</queueNum></class><class id="leafhostVIP1"><parentId>innerconnVIP</parentId><rate type="int">30.0</rate><ceil type="int">37.5</ceil><burst type="int">1600</burst><cburst type="int">1600</cburst><level type="int">0</level><quantum type="int">1600</quantum><mbuffer type="int">60</mbuffer><priority>0</priority><queueNum type="int">22</queueNum></class><class id="leafhostVIP2"><parentId>innerconnVIP</parentId><rate type="int">30.0</rate><ceil type="int">37.5</ceil><burst type="int">1600</burst><cburst type="int">1600</cburst><level type="int">0</level><quantum type="int">1600</quantum><mbuffer type="int">60</mbuffer><priority>0</priority><queueNum type="int">23</queueNum></class><class id="leafhostVIP3"><parentId>innerconnVIP</parentId><rate type="int">30.0</rate><ceil type="int">37.5</ceil><burst type="int">1600</burst><cburst type="int">1600</cburst><level type="int">0</level><quantum type="int">1600</quantum><mbuffer type="int">60</mbuffer><priority>0</priority><queueNum type="int">24</queueNum></class><class id="leafhostVIP4"><parentId>innerconnVIP</parentId><rate type="int">30.0</rate><ceil type="int">37.5</ceil><burst type="int">1600</burst><cburst type="int">1600</cburst><level type="int">0</level><quantum type="int">1600</quantum><mbuffer type="int">60</mbuffer><priority>0</priority><queueNum type="int">25</queueNum></class><class id="leafhostVIP5"><parentId>innerconnVIP</parentId><rate type="int">30.0</rate><ceil type="int">37.5</ceil><burst type="int">1600</burst><cburst type="int">1600</cburst><level type="int">0</level><quantum type="int">1600</quantum><mbuffer type="int">60</mbuffer><priority>0</priority><queueNum type="int">26</queueNum></class><class id="innerconnVID"><parentId>root</parentId><rate type="int">5000.0</rate><ceil type="int">6250.0</ceil><burst type="int">1600</burst><cburst type="int">1600</cburst><level type="int">1</level><quantum type="int">1600</quantum><mbuffer type="int">60</mbuffer></class><class id="innerconnLVD"><parentId>root</parentId><rate type="int">10750.0</rate><ceil type="int">13437.5</ceil><burst type="int">1600</burst><cburst type="int">1600</cburst><level type="int">1</level><quantum type="int">1600</quantum><mbuffer type="int">60</mbuffer></class><class id="innerconnFDO"><parentId>root</parentId><rate type="int">4000.0</rate><ceil type="int">5000.0</ceil><burst type="int">1600</burst><cburst type="int">1600</cburst><level type="int">1</level><quantum type="int">1600</quantum><mbuffer type="int">60</mbuffer></class><class id="innerconnSSH"><parentId>root</parentId><rate type="int">60.0</rate><ceil type="int">75.0</ceil><burst type="int">1600</burst><cburst type="int">1600</cburst><level type="int">1</level><quantum type="int">1600</quantum><mbuffer type="int">60</mbuffer></class><class id="innerconnVIP"><parentId>root</parentId><rate type="int">180.0</rate><ceil type="int">225.0</ceil><burst type="int">1600</burst><cburst type="int">1600</cburst><level type="int">1</level><quantum type="int">1600</quantum><mbuffer type="int">60</mbuffer></class></config>